fpr_infra/__init__.py
fpr_infra/aws.py
fpr_infra/packer.py
fpr_infra/plugin.py
fpr_infra/modules/__init__.py
fpr_infra/modules/files.py
fpr_infra/modules/nginx.py
fpr_infra-0.1.16.dist-info/DESCRIPTION.rst
fpr_infra-0.1.16.dist-info/METADATA
fpr_infra-0.1.16.dist-info/RECORD
fpr_infra-0.1.16.dist-info/WHEEL
fpr_infra-0.1.16.dist-info/entry_points.txt
fpr_infra-0.1.16.dist-info/metadata.json
fpr_infra-0.1.16.dist-info/top_level.txt
