Metadata-Version: 2.0
Name: fpr-infra
Version: 0.1.16
Summary: Python utilities for packer/pyinfra/pytest deploiments
Home-page: UNKNOWN
Author: Guillaume Doumenc
Author-email: gdoumenc@fpr-coworks.com
License: UNKNOWN
Platform: UNKNOWN
Classifier: Development Status :: 3 - Alpha
Classifier: Programming Language :: Python :: 3.6
Classifier: Framework :: Pytest
Requires-Python: >=3.6
Requires-Dist: click
Requires-Dist: testinfra
Requires-Dist: boto3
Requires-Dist: pyinfra
